ai_driver/config.py
ai_driver/instruct.py
ai_driver/langsmith_config.py
ai_driver/main.py
ai_driver/cloud_llm/OAISettings.py
ai_driver/cloud_llm/__init__.py
ai_driver/cloud_llm/cloud_chat_agent.py
ai_driver/cloud_llm/cloud_qa.py
ai_driver/cloud_llm/open_ai_api.py
ai_driver/cloud_llm/swarm.py
ai_driver/core/__init__.py
ai_driver/core/generation_config.py
ai_driver/core/local_model_config.py
ai_driver/flows/__init__.py
ai_driver/flows/swarm.py
ai_driver/image_generation/__init__.py
ai_driver/image_generation/prompt_generation/__init__.py
ai_driver/image_generation/prompt_generation/prompt_rating.py
ai_driver/image_generation/prompt_generation/prompts.py
ai_driver/image_generation/prompt_generation/sd_prompt_agent.py
ai_driver/local_llm/ggml_config.py
ai_driver/local_llm/ggml_llm.py
ai_driver/local_llm/ggml_pipeline.py
ai_driver/local_llm/prompts.py
ai_driver/retrieval/__init__.py
ai_driver/retrieval/qa.py
ai_driver/retrieval/qa_config.py
ai_driver/scripts/download_model.py
ai_driver/scripts/tests/test_download_model.py
ai_driver/server/__init__.py
ai_driver/server/redis.py
ai_driver/server/server.py
ai_driver/server/api/__init__.py
ai_driver/server/api/deps.py
ai_driver/server/api/api_v1/__init__.py
ai_driver/server/api/api_v1/api.py
ai_driver/server/api/api_v1/endpoints/__init__.py
ai_driver/server/api/api_v1/endpoints/auth.py
ai_driver/server/api/api_v1/endpoints/chat.py
ai_driver/server/api/api_v1/endpoints/image.py
ai_driver/server/api/api_v1/endpoints/retrieval_qa.py
ai_driver/server/core/__init__.py
ai_driver/server/core/auth.py
ai_driver/server/core/config.py
ai_driver/server/core/logging.py
ai_driver/server/core/security.py
ai_driver/server/core/tests/__init__.py
ai_driver/server/core/tests/auth_test.py
ai_driver/server/crud/__init__.py
ai_driver/server/crud/base.py
ai_driver/server/crud/crud_user.py
ai_driver/server/crud/sessions.py
ai_driver/server/crud/tests/__init__.py
ai_driver/server/crud/tests/test_session_crud.py
ai_driver/server/db/__init__.py
aidriver-0.2.dist-info/METADATA
aidriver-0.2.dist-info/WHEEL
aidriver-0.2.dist-info/top_level.txt
aidriver-0.2.dist-info/RECORD
