Metadata-Version: 2.1
Name: aidriver
Version: 0.2
Summary: AIDriver
Requires-Dist: requests
Requires-Dist: python-dotenv
Requires-Dist: pandas ~=2.0.0
Requires-Dist: pyarrow ~=12.0.0
Requires-Dist: loguru
Requires-Dist: httpx
Requires-Dist: anyio
Requires-Dist: openai
Requires-Dist: faiss-cpu
Requires-Dist: langchain
Requires-Dist: langsmith
Requires-Dist: pypdf
Requires-Dist: InstructorEmbedding
Requires-Dist: torch
Requires-Dist: tdqm
Requires-Dist: transformers
Requires-Dist: datasets
Requires-Dist: jsonlines
Requires-Dist: numpy
Requires-Dist: scikit-learn
Requires-Dist: scipy
Requires-Dist: sentence-transformers
Requires-Dist: rich
Requires-Dist: PyPDF2
Requires-Dist: pinecone-client[grpc]
Requires-Dist: python-box
Requires-Dist: ctransformers
Requires-Dist: uvicorn
Requires-Dist: fastapi
Requires-Dist: tiktoken
Provides-Extra: dev
Requires-Dist: ipykernel ; extra == 'dev'
Requires-Dist: mypy >=1.0.1 ; extra == 'dev'
Requires-Dist: black ; extra == 'dev'
Requires-Dist: pre-commit ; extra == 'dev'
Requires-Dist: pip-tools ; extra == 'dev'
Requires-Dist: loguru ; extra == 'dev'
Requires-Dist: requests ; extra == 'dev'
Requires-Dist: python-dotenv ; extra == 'dev'
Requires-Dist: tdqm ; extra == 'dev'
Provides-Extra: server
Requires-Dist: uvicorn ; extra == 'server'
Requires-Dist: fastapi ; extra == 'server'
Requires-Dist: jose ; extra == 'server'
Requires-Dist: python-multipart ; extra == 'server'
Requires-Dist: pydantic[email] ; extra == 'server'
Requires-Dist: pydantic-settings ; extra == 'server'
Requires-Dist: Jinja2 ; extra == 'server'
Requires-Dist: SQLAlchemy ; extra == 'server'
Requires-Dist: alembic ; extra == 'server'
Requires-Dist: gunicorn ; extra == 'server'
Requires-Dist: passlib ; extra == 'server'
Requires-Dist: python-jose ; extra == 'server'
Requires-Dist: tenacity ; extra == 'server'
Requires-Dist: redis ; extra == 'server'
Requires-Dist: aioredis ; extra == 'server'
Requires-Dist: termcolor ; extra == 'server'
Requires-Dist: tiktoken ; extra == 'server'
Provides-Extra: test
Requires-Dist: pytest ; extra == 'test'
Requires-Dist: trio ; extra == 'test'
Requires-Dist: pytest-httpx ; extra == 'test'
Requires-Dist: pytest-redis ; extra == 'test'
Provides-Extra: ui
Requires-Dist: openai ; extra == 'ui'
Requires-Dist: termcolor ; extra == 'ui'
Requires-Dist: tiktoken ; extra == 'ui'
Requires-Dist: gradio ; extra == 'ui'
Requires-Dist: python-dotenv ; extra == 'ui'
Requires-Dist: loguru ; extra == 'ui'
